hatanaka-2.8.1.data/purelib/hatanaka/__init__.py
hatanaka-2.8.1.data/purelib/hatanaka/cli.py
hatanaka-2.8.1.data/purelib/hatanaka/general_compression.py
hatanaka-2.8.1.data/purelib/hatanaka/hatanaka.py
hatanaka-2.8.1.data/purelib/hatanaka/bin/__init__.py
hatanaka-2.8.1.data/purelib/hatanaka/bin/crx2rnx
hatanaka-2.8.1.data/purelib/hatanaka/bin/rnx2crx
hatanaka-2.8.1.data/purelib/hatanaka/test/__init__.py
hatanaka-2.8.1.data/purelib/hatanaka/test/conftest.py
hatanaka-2.8.1.data/purelib/hatanaka/test/test_cli.py
hatanaka-2.8.1.data/purelib/hatanaka/test/test_general_compression.py
hatanaka-2.8.1.data/purelib/hatanaka/test/test_hatanaka.py
hatanaka-2.8.1.data/purelib/hatanaka/test/test_on_disk_functions.py
hatanaka-2.8.1.data/purelib/hatanaka/test/data/__init__.py
hatanaka-2.8.1.data/purelib/hatanaka/test/data/sample.crx
hatanaka-2.8.1.data/purelib/hatanaka/test/data/sample.crx.Z
hatanaka-2.8.1.data/purelib/hatanaka/test/data/sample.crx.bz2
hatanaka-2.8.1.data/purelib/hatanaka/test/data/sample.crx.gz
hatanaka-2.8.1.data/purelib/hatanaka/test/data/sample.crx.zip
hatanaka-2.8.1.data/purelib/hatanaka/test/data/sample.rnx
hatanaka-2.8.1.data/purelib/hatanaka/test/data/sample.rnx.Z
hatanaka-2.8.1.data/purelib/hatanaka/test/data/sample.rnx.bz2
hatanaka-2.8.1.data/purelib/hatanaka/test/data/sample.rnx.gz
hatanaka-2.8.1.data/purelib/hatanaka/test/data/sample.rnx.zip
hatanaka-2.8.1.dist-info/LICENSE
hatanaka-2.8.1.dist-info/METADATA
hatanaka-2.8.1.dist-info/WHEEL
hatanaka-2.8.1.dist-info/entry_points.txt
hatanaka-2.8.1.dist-info/top_level.txt
hatanaka-2.8.1.dist-info/RECORD
