Metadata-Version: 2.1
Name: hatanaka
Version: 2.8.1
Summary: Effortlessly compress / decompress any RINEX file
Home-page: https://github.com/valgur/hatanaka
Author: Martin Valgur
Author-email: martin.valgur@gmail.com
Keywords: RINEX,Hatanaka compression,GNSS
Classifier: License :: OSI Approved :: MIT License
Classifier: Operating System :: OS Independent
Classifier: Programming Language :: Python :: 3
Classifier: Environment :: Console
Classifier: Topic :: Scientific/Engineering
Requires-Python: >=3.6
License-File: LICENSE
Requires-Dist: importlib-resources
Requires-Dist: ncompress
Provides-Extra: dev
Requires-Dist: pytest ; extra == 'dev'
Provides-Extra: tests
Requires-Dist: pytest ; extra == 'tests'
